{
   "format_version":"1.8.0",
   "minecraft:entity":{
      "description":{
         "identifier":"ccl:wasp",
         "is_spawnable":true,
         "is_summonable":true,
         "is_experimental":false
      },
      "component_groups":{
         "ccl:wasp_adult":{
            "minecraft:behavior.breed":{
               "priority":3,
               "speed_multiplier":1.0
            },
            "minecraft:breedable":{
               "requireTame":false,
               "breedItems":"wheat",
               "breedsWith":{
                  "mateType":"ccl:wasp",
                  "babyType":"ccl:wasp",
                  "breed_event":{
                     "event":"minecraft:entity_born",
                     "target":"baby"
                  }
               }
            },
            "minecraft:scale":{
               "value":0.25
            }
         }
      },
      "components":{
         "minecraft:type_family":{
            "family":[
               "wasp",
               "mob"
            ]
         },
         "minecraft:loot":{
            "table":"loot_tables/wasp.json"
         },
         "minecraft:breathable":{
            "totalSupply":15,
            "suffocateTime":0
         },
         "minecraft:navigation.walk":{
            "can_path_over_water":false,
            "avoid_water":true,
            "avoid_damage_blocks":true
         },
         "minecraft:movement":{
            "value":0.05
         },
         "minecraft:navigation.float":{
            "can_path_over_water":true
         },
         "minecraft:movement.basic":{

         },
         "minecraft:jump.static":{

         },
         "minecraft:behavior.float":{
            "priority":0
         },
         "minecraft:behavior.float_wander":{
            "xz_dist":10,
            "y_dist":7,
            "y_offset":0,
            "random_reselect":true,
            "float_duration":[
               1.5,
               2.5
            ]
         },
         "minecraft:can_fly":{

         },
         "minecraft:can_climb":{

         },
         "minecraft:collision_box":{
            "width":0.5,
            "height":0.6
         },
         "minecraft:nameable":{

         },
         "minecraft:health":{
            "value":10,
            "max":10
         },
         "minecraft:behavior.mount_pathing":{
            "priority":7,
            "speed_multiplier":1.0,
            "target_dist":0.0,
            "track_target":true
         },
         "minecraft:behavior.tempt":{
            "priority":4,
            "speed_multiplier":1.05,
            "items":[
               "wheat"
            ]
         },
         "minecraft:behavior.random_stroll":{
            "priority":6,
            "speed_multiplier":0.1
         },
         "minecraft:behavior.look_at_player":{
            "priority":7,
            "look_distance":6.0,
            "probability":0.02
         },
         "minecraft:behavior.random_look_around":{
            "priority":9
         },
         "minecraft:physics":{

         },
         "minecraft:damage_sensor":{
            "triggers":{
               "cause":"fall",
               "deals_damage":false
            }
         },
         "minecraft:fall_damage":{
            "value":0.0
         }
      },
      "events":{
         "minecraft:entity_spawned":{
            "add":{
               "component_groups":[
                  "ccl:wasp_adult"
               ]
            }
         }
      }
   }
}
